{"index.md":"CYwumBIf","page.md":"CjmxexVN","page_1.md":"Cv2-B9EY","page_index.md":"CYN89QrT","pages_about.md":"DkdUsUDl","pages_archives.md":"DSWZ00tq","pages_categories.md":"Fe5Ccly8","pages_categories_随便说说.md":"BB3Qa0zS","pages_categories_题解.md":"BNwrEoez","pages_cc.md":"C9-TdAQQ","pages_index.md":"B7hnbtSN","pages_link.md":"DBYXnU7h","pages_nazo_8543.md":"Cz-mT6DZ","pages_nazo_answer.md":"0jcJDKwp","pages_nazo_b51ba162dd6b9886ef9b1e6d31713ea29f41a79366149031bb1301da865c12c2.md":"DDSkRJZJ","pages_nazo_characteristic.md":"CZMpumWr","pages_nazo_index.md":"DcFESDox","pages_nazo_stage1.md":"CqP4UvlZ","pages_nazo_stage2.md":"DvI8x3iT","pages_nazo_stage3.md":"kGn0bFGC","pages_privacy.md":"Ce9YqQ7k","pages_project.md":"S9Yzd9Qc","pages_tags.md":"D1_ulEpx","pages_tags_hello.md":"B2RdNobh","pages_tags_原创.md":"Bhg5Oiyz","pages_visitorcounting.md":"H_W9G-VI","posts_2024_1010.md":"B9a31S4v","posts_2025_0912.md":"C_XJhsxw","posts_2025_0913.md":"ClG5hVWx","posts_2025_0915.md":"BIuygnXJ"}
